readmex/__init__.py
readmex/__main__.py
readmex/code_rag.py
readmex/config.py
readmex/core.py
readmex/website_core.py
readmex/config/dependency_config.json
readmex/config/ignore_patterns.json
readmex/config/language_mapping.json
readmex/images/logo.png
readmex/images/screenshot.png
readmex/templates/BLANK_README.md
readmex/utils/__init__.py
readmex/utils/cli.py
readmex/utils/dependency_analyzer.py
readmex/utils/file_handler.py
readmex/utils/language_analyzer.py
readmex/utils/logo_generator.py
readmex/utils/model_client.py
readmex-0.3.0.dist-info/licenses/LICENSE.txt
readmex-0.3.0.dist-info/METADATA
readmex-0.3.0.dist-info/WHEEL
readmex-0.3.0.dist-info/entry_points.txt
readmex-0.3.0.dist-info/top_level.txt
readmex-0.3.0.dist-info/RECORD
