Metadata-Version: 2.4
Name: readmex
Version: 0.3.0
Summary: A tool to automatically generate README files for your projects.
Author-email: stone91 <m370025263@gmail.com>, lintao <lint22@mails.tsinghua.edu.cn>
Project-URL: Homepage, https://github.com/aibox22/readmex
Project-URL: Bug Tracker, https://github.com/aibox22/readmex/issues
Classifier: Programming Language :: Python :: 3
Classifier: License :: OSI Approved :: MIT License
Classifier: Operating System :: OS Independent
Requires-Python: >=3.8
License-File: LICENSE.txt
Requires-Dist: python-dotenv>=0.15.0
Requires-Dist: numpy>=1.21.0
Requires-Dist: openai>=0.11.0
Requires-Dist: rich>=10.0.0
Requires-Dist: requests>=2.25.0
Requires-Dist: pytest>=6.0.0
Requires-Dist: sentence-transformers>=2.0.0
Requires-Dist: faiss-cpu>=1.7.0
Dynamic: license-file
